tremendous/__init__.py
tremendous/exception.py
tremendous/serializer.py
tremendous/service/__init__.py
tremendous/service/http_service.py
tremendous/service/tremendous_service.py
TremendousClient-0.0.7.dist-info/LICENSE
TremendousClient-0.0.7.dist-info/METADATA
TremendousClient-0.0.7.dist-info/WHEEL
TremendousClient-0.0.7.dist-info/top_level.txt
TremendousClient-0.0.7.dist-info/RECORD
